{
  "uid": "ktrdr-worker-status",
  "title": "KTRDR Worker Status",
  "description": "Status of KTRDR workers including health, resources, and availability",
  "schemaVersion": 39,
  "timezone": "browser",
  "refresh": "30s",
  "time": {
    "from": "now-1h",
    "to": "now"
  },
  "editable": true,
  "fiscalYearStartMonth": 0,
  "graphTooltip": 0,
  "links": [],
  "panels": [
    {
      "id": 1,
      "type": "stat",
      "title": "Registered Workers",
      "description": "Total number of registered workers",
      "gridPos": {
        "x": 0,
        "y": 0,
        "w": 6,
        "h": 4
      },
      "datasource": {
        "type": "prometheus",
        "uid": "prometheus"
      },
      "targets": [
        {
          "datasource": {
            "type": "prometheus",
            "uid": "prometheus"
          },
          "expr": "count(up{instance=~\".*:500[3-8]\"})",
          "refId": "A"
        }
      ],
      "options": {
        "colorMode": "value",
        "graphMode": "none",
        "justifyMode": "auto",
        "orientation": "auto",
        "reduceOptions": {
          "calcs": ["lastNotNull"],
          "fields": "",
          "values": false
        },
        "textMode": "auto"
      },
      "fieldConfig": {
        "defaults": {
          "thresholds": {
            "mode": "absolute",
            "steps": [
              {"color": "green", "value": null}
            ]
          },
          "mappings": [],
          "unit": "none"
        },
        "overrides": []
      }
    },
    {
      "id": 2,
      "type": "stat",
      "title": "Healthy Workers",
      "description": "Number of workers currently healthy",
      "gridPos": {
        "x": 6,
        "y": 0,
        "w": 6,
        "h": 4
      },
      "datasource": {
        "type": "prometheus",
        "uid": "prometheus"
      },
      "targets": [
        {
          "datasource": {
            "type": "prometheus",
            "uid": "prometheus"
          },
          "expr": "sum(up{instance=~\".*:500[3-8]\"})",
          "refId": "A"
        }
      ],
      "options": {
        "colorMode": "value",
        "graphMode": "none",
        "justifyMode": "auto",
        "orientation": "auto",
        "reduceOptions": {
          "calcs": ["lastNotNull"],
          "fields": "",
          "values": false
        },
        "textMode": "auto"
      },
      "fieldConfig": {
        "defaults": {
          "thresholds": {
            "mode": "absolute",
            "steps": [
              {"color": "red", "value": null},
              {"color": "yellow", "value": 2},
              {"color": "green", "value": 4}
            ]
          },
          "mappings": [],
          "unit": "none"
        },
        "overrides": []
      }
    },
    {
      "id": 3,
      "type": "stat",
      "title": "Backtest Workers",
      "description": "Number of backtest workers (ports 5003, 5004)",
      "gridPos": {
        "x": 12,
        "y": 0,
        "w": 6,
        "h": 4
      },
      "datasource": {
        "type": "prometheus",
        "uid": "prometheus"
      },
      "targets": [
        {
          "datasource": {
            "type": "prometheus",
            "uid": "prometheus"
          },
          "expr": "sum(up{instance=~\".*:500[34]\"})",
          "refId": "A"
        }
      ],
      "options": {
        "colorMode": "value",
        "graphMode": "none",
        "justifyMode": "auto",
        "orientation": "auto",
        "reduceOptions": {
          "calcs": ["lastNotNull"],
          "fields": "",
          "values": false
        },
        "textMode": "auto"
      },
      "fieldConfig": {
        "defaults": {
          "thresholds": {
            "mode": "absolute",
            "steps": [
              {"color": "green", "value": null}
            ]
          },
          "mappings": [],
          "unit": "none"
        },
        "overrides": []
      }
    },
    {
      "id": 4,
      "type": "stat",
      "title": "Training Workers",
      "description": "Number of training workers (ports 5005, 5006)",
      "gridPos": {
        "x": 18,
        "y": 0,
        "w": 6,
        "h": 4
      },
      "datasource": {
        "type": "prometheus",
        "uid": "prometheus"
      },
      "targets": [
        {
          "datasource": {
            "type": "prometheus",
            "uid": "prometheus"
          },
          "expr": "sum(up{instance=~\".*:500[56]\"})",
          "refId": "A"
        }
      ],
      "options": {
        "colorMode": "value",
        "graphMode": "none",
        "justifyMode": "auto",
        "orientation": "auto",
        "reduceOptions": {
          "calcs": ["lastNotNull"],
          "fields": "",
          "values": false
        },
        "textMode": "auto"
      },
      "fieldConfig": {
        "defaults": {
          "thresholds": {
            "mode": "absolute",
            "steps": [
              {"color": "green", "value": null}
            ]
          },
          "mappings": [],
          "unit": "none"
        },
        "overrides": []
      }
    },
    {
      "id": 5,
      "type": "table",
      "title": "Worker Health Matrix",
      "description": "Detailed status of each worker",
      "gridPos": {
        "x": 0,
        "y": 4,
        "w": 24,
        "h": 6
      },
      "datasource": {
        "type": "prometheus",
        "uid": "prometheus"
      },
      "targets": [
        {
          "datasource": {
            "type": "prometheus",
            "uid": "prometheus"
          },
          "expr": "up{instance=~\".*:500[3-8]\"}",
          "format": "table",
          "instant": true,
          "refId": "A"
        }
      ],
      "options": {
        "showHeader": true,
        "cellHeight": "sm"
      },
      "fieldConfig": {
        "defaults": {
          "custom": {
            "align": "auto",
            "cellOptions": {
              "type": "auto"
            },
            "inspect": false
          },
          "mappings": [
            {
              "options": {
                "0": {"text": "Down", "color": "red"},
                "1": {"text": "Up", "color": "green"}
              },
              "type": "value"
            }
          ],
          "thresholds": {
            "mode": "absolute",
            "steps": [
              {"color": "red", "value": null},
              {"color": "green", "value": 1}
            ]
          }
        },
        "overrides": [
          {
            "matcher": {"id": "byName", "options": "instance"},
            "properties": [
              {"id": "displayName", "value": "Worker"}
            ]
          },
          {
            "matcher": {"id": "byName", "options": "Value"},
            "properties": [
              {"id": "displayName", "value": "Status"}
            ]
          }
        ]
      },
      "transformations": [
        {
          "id": "organize",
          "options": {
            "excludeByName": {
              "Time": true,
              "__name__": true,
              "job": true
            },
            "indexByName": {},
            "renameByName": {}
          }
        }
      ]
    },
    {
      "id": 6,
      "type": "timeseries",
      "title": "Worker CPU Usage",
      "description": "CPU usage per worker over time",
      "gridPos": {
        "x": 0,
        "y": 10,
        "w": 12,
        "h": 8
      },
      "datasource": {
        "type": "prometheus",
        "uid": "prometheus"
      },
      "targets": [
        {
          "datasource": {
            "type": "prometheus",
            "uid": "prometheus"
          },
          "expr": "rate(process_cpu_seconds_total{instance=~\".*:500[3-8]\"}[5m]) * 100",
          "legendFormat": "{{instance}}",
          "refId": "A"
        }
      ],
      "options": {
        "legend": {
          "displayMode": "list",
          "placement": "bottom",
          "showLegend": true
        },
        "tooltip": {
          "mode": "multi",
          "sort": "desc"
        }
      },
      "fieldConfig": {
        "defaults": {
          "custom": {
            "drawStyle": "line",
            "lineInterpolation": "smooth",
            "fillOpacity": 10,
            "gradientMode": "none",
            "spanNulls": false,
            "showPoints": "never",
            "pointSize": 5,
            "stacking": {
              "mode": "none"
            },
            "axisPlacement": "auto",
            "axisLabel": "",
            "scaleDistribution": {
              "type": "linear"
            }
          },
          "color": {
            "mode": "palette-classic"
          },
          "thresholds": {
            "mode": "absolute",
            "steps": [
              {"color": "green", "value": null}
            ]
          },
          "mappings": [],
          "unit": "percent"
        },
        "overrides": []
      }
    },
    {
      "id": 7,
      "type": "timeseries",
      "title": "Worker Memory Usage",
      "description": "Memory usage per worker over time",
      "gridPos": {
        "x": 12,
        "y": 10,
        "w": 12,
        "h": 8
      },
      "datasource": {
        "type": "prometheus",
        "uid": "prometheus"
      },
      "targets": [
        {
          "datasource": {
            "type": "prometheus",
            "uid": "prometheus"
          },
          "expr": "process_resident_memory_bytes{instance=~\".*:500[3-8]\"}",
          "legendFormat": "{{instance}}",
          "refId": "A"
        }
      ],
      "options": {
        "legend": {
          "displayMode": "list",
          "placement": "bottom",
          "showLegend": true
        },
        "tooltip": {
          "mode": "multi",
          "sort": "desc"
        }
      },
      "fieldConfig": {
        "defaults": {
          "custom": {
            "drawStyle": "line",
            "lineInterpolation": "smooth",
            "fillOpacity": 10,
            "gradientMode": "none",
            "spanNulls": false,
            "showPoints": "never",
            "pointSize": 5,
            "stacking": {
              "mode": "none"
            },
            "axisPlacement": "auto",
            "axisLabel": "",
            "scaleDistribution": {
              "type": "linear"
            }
          },
          "color": {
            "mode": "palette-classic"
          },
          "thresholds": {
            "mode": "absolute",
            "steps": [
              {"color": "green", "value": null}
            ]
          },
          "mappings": [],
          "unit": "bytes"
        },
        "overrides": []
      }
    },
    {
      "id": 8,
      "type": "state-timeline",
      "title": "Worker Availability Timeline",
      "description": "Worker up/down status over time",
      "gridPos": {
        "x": 0,
        "y": 18,
        "w": 24,
        "h": 6
      },
      "datasource": {
        "type": "prometheus",
        "uid": "prometheus"
      },
      "targets": [
        {
          "datasource": {
            "type": "prometheus",
            "uid": "prometheus"
          },
          "expr": "up{instance=~\".*:500[3-8]\"}",
          "legendFormat": "{{instance}}",
          "refId": "A"
        }
      ],
      "options": {
        "showValue": "auto",
        "rowHeight": 0.9,
        "mergeValues": true,
        "alignValue": "center",
        "legend": {
          "displayMode": "list",
          "placement": "bottom",
          "showLegend": true
        },
        "tooltip": {
          "mode": "single"
        }
      },
      "fieldConfig": {
        "defaults": {
          "custom": {
            "lineWidth": 0,
            "fillOpacity": 70
          },
          "color": {
            "mode": "thresholds"
          },
          "thresholds": {
            "mode": "absolute",
            "steps": [
              {"color": "red", "value": null},
              {"color": "green", "value": 1}
            ]
          },
          "mappings": [
            {
              "options": {
                "0": {"text": "Down", "color": "red"},
                "1": {"text": "Up", "color": "green"}
              },
              "type": "value"
            }
          ]
        },
        "overrides": []
      }
    }
  ],
  "templating": {
    "list": []
  },
  "annotations": {
    "list": [
      {
        "builtIn": 1,
        "datasource": {
          "type": "grafana",
          "uid": "-- Grafana --"
        },
        "enable": true,
        "hide": true,
        "iconColor": "rgba(0, 211, 255, 1)",
        "name": "Annotations & Alerts",
        "type": "dashboard"
      }
    ]
  },
  "version": 1
}
